{
"type": "FeatureCollection",
"name": "sekat_kanal",
"crs": { "type": "name", "properties": { "name": "urn:ogc:def:crs:OGC:1.3:CRS84" } },
"features": [
{ "type": "Feature", "properties": { "No": 1, "Kabupaten": "Bengkalis", "Kecamatan": "Bandar Laksamana", "Desa": "Sepahat", "X": 101.8076, "Y": 1.5716, "Tahun": 2021, "Ket": "GEC", "Foto": "CB_Sepahat.JPG", "Foto_2": "CB_Sepahat (2).JPG" }, "geometry": { "type": "Point", "coordinates": [ 101.8076, 1.5716 ] } },
{ "type": "Feature", "properties": { "No": 2, "Kabupaten": "Bengkalis", "Kecamatan": "Bandar Laksamana", "Desa": "Sepahat", "X": 101.81161, "Y": 1.568655, "Tahun": 2023, "Ket": "GEC", "Foto": "CB_Sepahat_2023.JPG", "Foto_2": null }, "geometry": { "type": "Point", "coordinates": [ 101.81161, 1.568655 ] } },
{ "type": "Feature", "properties": { "No": 3, "Kabupaten": "Bengkalis", "Kecamatan": "Bandar Laksamana", "Desa": "Temiang", "X": 101.922295, "Y": 1.478675, "Tahun": 2022, "Ket": "GEC", "Foto": "CB_Temiang_2022.JPG", "Foto_2": "CB_Temiang_2022_1.JPG" }, "geometry": { "type": "Point", "coordinates": [ 101.922295353787277, 1.47867464621274 ] } },
{ "type": "Feature", "properties": { "No": 4, "Kabupaten": "Bengkalis", "Kecamatan": "Bandar Laksamana", "Desa": "Temiang", "X": 101.928592, "Y": 1.479234, "Tahun": 2023, "Ket": "GEC", "Foto": "CB_Temiang_2023.JPG", "Foto_2": null }, "geometry": { "type": "Point", "coordinates": [ 101.928591666666676, 1.479234444444445 ] } },
{ "type": "Feature", "properties": { "No": 5, "Kabupaten": "Bengkalis", "Kecamatan": "Bandar Laksamana", "Desa": "Temiang", "X": 101.92487, "Y": 1.47571, "Tahun": 2024, "Ket": "GEC", "Foto": "CB_Temiang_2024.JPG", "Foto_2": null }, "geometry": { "type": "Point", "coordinates": [ 101.92487, 1.47571 ] } },
{ "type": "Feature", "properties": { "No": 6, "Kabupaten": "Bengkalis", "Kecamatan": "Bengkalis", "Desa": "Pematang Duku", "X": 102.294667, "Y": 1.455018, "Tahun": 2025, "Ket": "PPCF", "Foto": "CB_PD_3.JPG", "Foto_2": null }, "geometry": { "type": "Point", "coordinates": [ 102.294667, 1.455018 ] } },
{ "type": "Feature", "properties": { "No": 7, "Kabupaten": "Bengkalis", "Kecamatan": "Bengkalis", "Desa": "Pematang Duku", "X": 102.294373, "Y": 1.460889, "Tahun": 2025, "Ket": "PPCF", "Foto": "CB_PD_4.JPG", "Foto_2": null }, "geometry": { "type": "Point", "coordinates": [ 102.29437267424791, 1.460889443911205 ] } },
{ "type": "Feature", "properties": { "No": 8, "Kabupaten": "Bengkalis", "Kecamatan": "Bengkalis", "Desa": "Pematang Duku", "X": 102.300522, "Y": 1.455571, "Tahun": 2025, "Ket": "PPCF", "Foto": "CB_PD_1.JPG", "Foto_2": null }, "geometry": { "type": "Point", "coordinates": [ 102.300522, 1.455571 ] } },
{ "type": "Feature", "properties": { "No": 9, "Kabupaten": "Bengkalis", "Kecamatan": "Bengkalis", "Desa": "Pematang Duku", "X": 102.30033, "Y": 1.458222, "Tahun": 2025, "Ket": "PPCF", "Foto": "CB_PD_2.JPG", "Foto_2": null }, "geometry": { "type": "Point", "coordinates": [ 102.30033, 1.458222 ] } },
{ "type": "Feature", "properties": { "No": 11, "Kabupaten": "Siak", "Kecamatan": "Sungai Apit", "Desa": "Tanjung Kuras", "X": 102.17396, "Y": 1.16694, "Tahun": 2024, "Ket": "GEC", "Foto": "CB_Tj_kuras_2024.JPG", "Foto_2": null }, "geometry": { "type": "Point", "coordinates": [ 102.17396, 1.16694 ] } },
{ "type": "Feature", "properties": { "No": 10, "Kabupaten": "Bengkalis", "Kecamatan": "Bukit Batu", "Desa": "Buruk Bakul", "X": 102.038444, "Y": 1.419, "Tahun": 2025, "Ket": "GEC", "Foto": "CB_Buruk Bakul 2025.JPG", "Foto_2": "CB_Buruk Bakul 2025_1.JPG" }, "geometry": { "type": "Point", "coordinates": [ 102.038444444444437, 1.419 ] } }
]
}
