{"type":"FeatureCollection","name":"nursery_mangrove","crs":{"type":"name","properties":{"name":"urn:ogc:def:crs:OGC:1.3:CRS84"}},"features":[{"type":"Feature","properties":{"Id":5,"Kabupaten":"Siak","Kecamatan":"Sungai Apit","Desa":"Tanjung Kuras","X":102.167861,"Y":1.197278,"Ket":null,"Tahun":null,"Object_ID":"NURSERY-TANJUNG-KURAS-NA-001","Nama_Objek":"Rumah Pembibitan Mangrove – Tanjung Kuras","Kategori":"Pembibitan Mangrove","Source_Layer":"nursery_mangrove","Status_Objek":"Aktif"},"geometry":{"type":"Point","coordinates":[102.16786111111112,1.197277778570933]}}]}